flask_classful.py
Flask_Classful-0.14.2.dist-info/AUTHORS.md
Flask_Classful-0.14.2.dist-info/LICENSE
Flask_Classful-0.14.2.dist-info/METADATA
Flask_Classful-0.14.2.dist-info/WHEEL
Flask_Classful-0.14.2.dist-info/top_level.txt
Flask_Classful-0.14.2.dist-info/RECORD
